Workbook

Sheet READ ME
B1: LATAM HEFA — Bridge-Financing Model (VCM → Compliance Handoff)
B2: Companion to: Appendix to Chapters 7 & 8 — Fuel-Based VCM White Space. Built 2026-05-23.
B4: WHAT THIS MODELS
B5: A HEFA renewable-fuel project in a deregulated LATAM geography (no domestic LCFS/RFS analog). The
B6: question: can a voluntary carbon / SAF book-and-claim revenue stream bridge the project across FID,
B7: until the molecules/attributes reach a compliance market OR local regulation arrives — and what happens
B8: to the economics at that handoff (the 'toll booth that closes behind you').
B10: THE CENTRAL INSIGHT (additionality inversion)
B11: The same physical plant has very different economics by destination. Where compliance revenue is rich
B12: (US: RIN+LCFS+45Z), the project is bankable on compliance alone → the VCM credit is NON-ADDITIONAL and
B13: the attribute is already claimed. The VCM bridge is only defensible in the pure-bridge case, where no
B14: regime claims the attribute and the credit is what makes the project pencil — and that revenue is FINITE.
... B31: • This is a teaching/screening tool, not investment advice.

Sheet Inputs
B1: INPUTS — every blue cell is yours to change
B2: Yellow = key assumptions to pressure-test. All values are industry-typical placeholders.
B4: PLANT & PRODUCTION
B5: Nameplate capacity | C5: 100 | D5: M gal/yr | E5: Mid-size HEFA SAF/renewable-diesel plant
B6: Utilization | C6: 0.9 | D6: % | E6: Steady-state run rate
B7: Annual production (calc) | C7: =C5*C6 -> 90 | D7: M gal/yr
B9: ECONOMICS (per gallon unless noted)
B10: Physical fuel price premium vs fossil | C10: 1.5 | D10: $/gal | E10: Spread over jet-A/diesel the buyer pays
B11: Feedstock + opex (variable) | C11: 3.2 | D11: $/gal | E11: UCO/tallow + processing; the swing cost
B12: Base fossil fuel value captured | C12: 2.3 | D12: $/gal | E12: What the molecule is worth as plain fuel
B13: Capex (total project) | C13: 500 | D13: $M | E13: Greenfield/retrofit; placeholder
B14: Annualized capex charge | C14: 0.45 | D14: $/gal | E14: Simplified: debt service + return per gal
B15: Hurdle: min margin to clear FID | C15: 0.5 | D15: $/gal | E15: Project must beat this to reach FID
B17: CARBON INTENSITY
B18: Fossil baseline CI | C18: 90 | D18: gCO2e/MJ | E18: Comparator for reductions
B19: Project HEFA CI | C19: 25 | D19: gCO2e/MJ | E19: Typical HEFA-from-waste pathway
B20: Energy per gallon | C20: 130 | D20: MJ/gal | E20: ~SAF/renewable diesel energy density
B21: CO2e reduced per gallon (calc) | C21: =(C18-C19)*C20/1000000 -> 0.00845 | D21: tCO2e/gal | E21: (CI_fossil - CI_proj) x MJ/gal / 1e6
B23: CREDIT / INCENTIVE PRICES (Q1-Q2 2026, verify before use)
B24: RIN value (D4/D5 equiv) | C24: 0.8 | D24: $/gal | E24: Source: D4 RIN market, 2026 (placeholder)
B25: LCFS credit price | C25: 63 | D25: $/tCO2e | E25: Source: ~$63/MT Q1 2026 (CARB/OPIS)
B26: 45Z production credit | C26: 0.75 | D26: $/gal | E26: Source: up to $1.00/gal by CI, thru 2029
B27: EU SAF compliance premium | C27: 1.8 | D27: $/gal | E27: ReFuelEU mandate-driven price uplift
B28: SAF book-and-claim cert price (REFERENCE ONLY) | C28: 2000 | D28: $/tCO2e | E28: Aviation-scarcity premium; NOT a clean abatement price - do not stack vs compliance
B29: VCM bridge price (realistic per-tonne proxy) | C29: 50 | D29: $/tCO2e | E29: Defensible fuel-pathway voluntary credit, ~$20-80/t; USED in bridge case
B31: BRIDGE & HANDOFF ASSUMPTIONS
B32: Bridge window (years VCM-eligible) | C32: 4 | D32: years | E32: Until local reg / compliance arrives
B33: Stranding haircut at handoff | C33: 0.4 | D33: % | E33: Share of VCM revenue LOST when reg claims attribute
B34: Compliance value post-handoff | C34: 1.2 | D34: $/gal | E34: What replaces VCM once regime arrives
B35: Discount rate | C35: 0.12 | D35: % | E35: For NPV of the 10-yr stream

Sheet Destination Compare
B1: SAME PLANT, THREE DESTINATIONS — margin per gallon
B2: The additionality inversion in one screen: richer compliance stack = less defensible VCM.
B4: Revenue / cost line ($/gal) | C4: US (RIN+LCFS+45Z) | D4: EU export (ReFuelEU) | E4: Pure VCM bridge | G4: Note
B5: Base fuel value | C5: =Inputs!C12 -> 2.3 | D5: =Inputs!C12 -> 2.3 | E5: =Inputs!C12 -> 2.3 | G5: Plain molecule value
B6: Physical premium | C6: =Inputs!C10 -> 1.5 | D6: =Inputs!C27 -> 1.8 | E6: =Inputs!C10 -> 1.5 | G6: EU mandate premium replaces generic premium
B7: RIN | C7: =Inputs!C24 -> 0.8 | D7: 0 | E7: 0 | G7: US only
B8: LCFS credit | C8: =Inputs!C25*Inputs!C21 -> 0.53235 | D8: 0 | E8: 0 | G8: US: $/tCO2e x tCO2e/gal
B9: 45Z | C9: =Inputs!C26 -> 0.75 | D9: 0 | E9: 0 | G9: US only, thru 2029
B10: VCM / book-and-claim (proxy price) | C10: 0 | D10: 0 | E10: =Inputs!C29*Inputs!C21 -> 0.4225 | G10: Bridge only; realistic per-tonne proxy, attribute unclaimed
B11: TOTAL REVENUE / gal | C11: =SUM(C5:C10) -> 5.88235 | D11: =SUM(D5:D10) -> 4.1 | E11: =SUM(E5:E10) -> 4.2225
B12: Less: feedstock + opex | C12: =-Inputs!C11 -> -3.2 | D12: =-Inputs!C11 -> -3.2 | E12: =-Inputs!C11 -> -3.2 | G12: Variable cost
B13: Less: annualized capex | C13: =-Inputs!C14 -> -0.45 | D13: =-Inputs!C14 -> -0.45 | E13: =-Inputs!C14 -> -0.45 | G13: Debt service + return
B14: NET MARGIN / gal | C14: =C11+C12+C13 -> 2.23235 | D14: =D11+D12+D13 -> 0.45 | E14: =E11+E12+E13 -> 0.5725
B15: Hurdle rate | C15: =Inputs!C15 -> 0.5 | D15: =Inputs!C15 -> 0.5 | E15: =Inputs!C15 -> 0.5 | G15: Min margin to clear FID
B16: CLEARS FID? | C16: =IF(C14>=C15,"YES","NO") -> YES | D16: =IF(D14>=D15,"YES","NO") -> NO | E16: =IF(E14>=E15,"YES","NO") -> YES
B17: VCM ADDITIONAL? | C17: =IF((C14-C10)>=C15,"NO: bankable w/o VCM","n/a") -> NO: bankable w/o VCM | D17: =IF((D14-D10)>=D15,"NO: bankable w/o VCM","n/a") -> n/a | E17: =IF(E10=0,"n/a",IF((E14-E10)<E15,"YES: VCM is the swing","NO: bankable w/o VCM")) -> YES: VCM is the swing | G17: The inversion: where compliance pays, VCM is non-additional & attribute already claimed.
B19: Annual net margin ($M/yr) | C19: =C14*Inputs!C7 -> 200.9115 | D19: =D14*Inputs!C7 -> 40.5 | E19: =E14*Inputs!C7 -> 51.525 | G19: Margin/gal x annual production
B21: READ THIS:
B22: • If US / EU columns clear FID without the VCM line, a voluntary credit there is NON-ADDITIONAL.
B23: • The Pure VCM bridge is the only column where the credit can be the swing vote that crosses FID.
B24: • But that bridge revenue is FINITE — see 'Bridge Handoff' tab for what happens when regulation arrives.
B26: THE UNIT MISMATCH (why you cannot naively stack VCM vs compliance)
B27: Instrument | C27: Quoted unit | D27: Per tCO2e | E27: Per gallon | G27: Why they don't compare
B28: RIN | C28: $/gal | D28: =Inputs!C24/Inputs!C21 -> 94.674556 | E28: =Inputs!C24 -> 0.8 | G28: Volumetric; converts to a modest per-tonne value
B29: LCFS credit | C29: $/tCO2e | D29: =Inputs!C25 -> 63 | E29: =Inputs!C25*Inputs!C21 -> 0.53235 | G29: Genuine carbon price; comparable to VCM proxy
B30: VCM bridge proxy | C30: $/tCO2e | D30: =Inputs!C29 -> 50 | E30: =Inputs!C29*Inputs!C21 -> 0.4225 | G30: Realistic fuel-pathway voluntary credit
B31: SAF cert (reference) | C31: $/tCO2e | D31: =Inputs!C28 -> 2000 | E31: =Inputs!C28*Inputs!C21 -> 16.9 | G31: DANGER: $/gal here exceeds whole fuel+stack. It is an aviation-scarcity premium for a DIFFERENT claim, not a clean abatement price. Do NOT multiply by gallons and stack.
B33: LESSON: RIN/45Z are quoted per gallon; LCFS and VCM per tCO2e. To compare, convert to ONE unit.
B34: A HEFA gallon abates only ~0.0085 tCO2e, so any per-tonne price x gallons looks tiny in $/gal terms —
B35: EXCEPT the SAF certificate price, which is NOT a carbon-abatement price. Multiplying it by a gallon's
B36: abatement (the naive stack) implied ~$17/gal — more than the entire fuel plus its compliance stack.
B37: That absurd result IS the lesson: the units lie, and SAF certs answer a different question than carbon credits.

Sheet Bridge Handoff
B1: BRIDGE HANDOFF — 10-year revenue path (Pure VCM bridge case)
B2: VCM revenue during the bridge window, then transition to compliance — with a stranding haircut at the handoff.
B4: Year | C4: 2026 | D4: 2027 | E4: 2028 | F4: 2029 | G4: 2030 | H4: 2031 | I4: 2032 | J4: 2033 | K4: 2034 | L4: 2035
B5: In bridge window? | C5: =IF(1<=Inputs!C32,"Bridge","Compliance") -> Bridge | D5: =IF(2<=Inputs!C32,"Bridge","Compliance") -> Bridge | E5: =IF(3<=Inputs!C32,"Bridge","Compliance") -> Bridge | F5: =IF(4<=Inputs!C32,"Bridge","Compliance") -> Bridge | G5: =IF(5<=Inputs!C32,"Bridge","Compliance") -> Compliance | H5: =IF(6<=Inputs!C32,"Bridge","Compliance") -> Compliance | I5: =IF(7<=Inputs!C32,"Bridge","Compliance") -> Compliance | J5: =IF(8<=Inputs!C32,"Bridge","Compliance") -> Compliance | K5: =IF(9<=Inputs!C32,"Bridge","Compliance") -> Compliance | L5: =IF(10<=Inputs!C32,"Bridge","Compliance") -> Compliance
B6: VCM rev ($/gal) | C6: =IF(1<=Inputs!C32,Inputs!C29*Inputs!C21,0) -> 0.4225 | D6: =IF(2<=Inputs!C32,Inputs!C29*Inputs!C21,0) -> 0.4225 | E6: =IF(3<=Inputs!C32,Inputs!C29*Inputs!C21,0) -> 0.4225 | F6: =IF(4<=Inputs!C32,Inputs!C29*Inputs!C21,0) -> 0.4225 | G6: =IF(5<=Inputs!C32,Inputs!C29*Inputs!C21,0) -> 0 | H6: =IF(6<=Inputs!C32,Inputs!C29*Inputs!C21,0) -> 0 | I6: =IF(7<=Inputs!C32,Inputs!C29*Inputs!C21,0) -> 0 | J6: =IF(8<=Inputs!C32,Inputs!C29*Inputs!C21,0) -> 0 | K6: =IF(9<=Inputs!C32,Inputs!C29*Inputs!C21,0) -> 0 | L6: =IF(10<=Inputs!C32,Inputs!C29*Inputs!C21,0) -> 0
B7: Compliance rev ($/gal) | C7: =IF(1<=Inputs!C32,0,Inputs!C34*(1-Inputs!C33)) -> 0 | D7: =IF(2<=Inputs!C32,0,Inputs!C34*(1-Inputs!C33)) -> 0 | E7: =IF(3<=Inputs!C32,0,Inputs!C34*(1-Inputs!C33)) -> 0 | F7: =IF(4<=Inputs!C32,0,Inputs!C34*(1-Inputs!C33)) -> 0 | G7: =IF(5<=Inputs!C32,0,Inputs!C34*(1-Inputs!C33)) -> 0.72 | H7: =IF(6<=Inputs!C32,0,Inputs!C34*(1-Inputs!C33)) -> 0.72 | I7: =IF(7<=Inputs!C32,0,Inputs!C34*(1-Inputs!C33)) -> 0.72 | J7: =IF(8<=Inputs!C32,0,Inputs!C34*(1-Inputs!C33)) -> 0.72 | K7: =IF(9<=Inputs!C32,0,Inputs!C34*(1-Inputs!C33)) -> 0.72 | L7: =IF(10<=Inputs!C32,0,Inputs!C34*(1-Inputs!C33)) -> 0.72
B8: Underlying fuel margin ($/gal) | C8: =Inputs!C12+Inputs!C10-Inputs!C11-Inputs!C14 -> 0.15 | D8: =Inputs!C12+Inputs!C10-Inputs!C11-Inputs!C14 -> 0.15 | E8: =Inputs!C12+Inputs!C10-Inputs!C11-Inputs!C14 -> 0.15 | F8: =Inputs!C12+Inputs!C10-Inputs!C11-Inputs!C14 -> 0.15 | G8: =Inputs!C12+Inputs!C10-Inputs!C11-Inputs!C14 -> 0.15 | H8: =Inputs!C12+Inputs!C10-Inputs!C11-Inputs!C14 -> 0.15 | I8: =Inputs!C12+Inputs!C10-Inputs!C11-Inputs!C14 -> 0.15 | J8: =Inputs!C12+Inputs!C10-Inputs!C11-Inputs!C14 -> 0.15 | K8: =Inputs!C12+Inputs!C10-Inputs!C11-Inputs!C14 -> 0.15 | L8: =Inputs!C12+Inputs!C10-Inputs!C11-Inputs!C14 -> 0.15
B9: TOTAL margin ($/gal) | C9: =C6+C7+C8 -> 0.5725 | D9: =D6+D7+D8 -> 0.5725 | E9: =E6+E7+E8 -> 0.5725 | F9: =F6+F7+F8 -> 0.5725 | G9: =G6+G7+G8 -> 0.87 | H9: =H6+H7+H8 -> 0.87 | I9: =I6+I7+I8 -> 0.87 | J9: =J6+J7+J8 -> 0.87 | ... L9: =L6+L7+L8 -> 0.87
B10: Annual margin ($M) | C10: =C9*Inputs!C7 -> 51.525 | D10: =D9*Inputs!C7 -> 51.525 | E10: =E9*Inputs!C7 -> 51.525 | F10: =F9*Inputs!C7 -> 51.525 | G10: =G9*Inputs!C7 -> 78.3 | H10: =H9*Inputs!C7 -> 78.3 | I10: =I9*Inputs!C7 -> 78.3 | J10: =J9*Inputs!C7 -> 78.3 | K10: =K9*Inputs!C7 -> 78.3 | L10: =L9*Inputs!C7 -> 78.3
B11: Discount factor | C11: =1/(1+Inputs!C35)^1 -> 0.89285714 | D11: =1/(1+Inputs!C35)^2 -> 0.79719388 | E11: =1/(1+Inputs!C35)^3 -> 0.71178025 | F11: =1/(1+Inputs!C35)^4 -> 0.63551808 | G11: =1/(1+Inputs!C35)^5 -> 0.56742686 | H11: =1/(1+Inputs!C35)^6 -> 0.50663112 | I11: =1/(1+Inputs!C35)^7 -> 0.45234922 | J11: =1/(1+Inputs!C35)^8 -> 0.40388323 | K11: =1/(1+Inputs!C35)^9 -> 0.36061002 | L11: =1/(1+Inputs!C35)^10 -> 0.32197324
B12: PV of annual margin ($M) | C12: =C10*C11 -> 46.004464 | D12: =D10*D11 -> 41.075415 | E12: =E10*E11 -> 36.674477 | F12: =F10*F11 -> 32.745069 | G12: =G10*G11 -> 44.429523 | H12: =H10*H11 -> 39.669217 | I12: =I10*I11 -> 35.418944 | J12: =J10*J11 -> 31.624057 | ... L12: =L10*L11 -> 25.210504
B14: NPV of 10-yr margin ($M) | C14: =SUM(C12:L12) -> 361.08743 | E14: Sum of discounted annual margins
B16: WHAT THE HANDOFF SHOWS:
B17: • During the bridge window the project lives on VCM revenue (attribute unclaimed by any regime).
B18: • When regulation arrives, the attribute is claimed by the compliance regime — VCM revenue STOPS.
B19: • The stranding haircut models value LOST in that transition (uncompensated claim, low price, or gap).
B20: • Underwrite the bridge on the FINITE VCM stream + the (haircut) compliance stream that follows — not on
B21: VCM revenue continuing forever. A long bridge window helps; a deep stranding haircut hurts.
B22: • Stress the two yellow drivers on Inputs: bridge window length and stranding haircut.
